convert_format/__init__.py
convert_format/convert_main/__init__.py
convert_format/convert_main/main.py
convert_format/csv_to_json/__init__.py
convert_format/csv_to_json/csv_to_json.py
csv_to_json_format-0.0.1.dist-info/METADATA
csv_to_json_format-0.0.1.dist-info/WHEEL
csv_to_json_format-0.0.1.dist-info/top_level.txt
csv_to_json_format-0.0.1.dist-info/RECORD
