Metadata-Version: 2.4
Name: csv_to_json_format
Version: 0.0.1
Summary: Uma ferramenta simples para converter arquivos CSV para JSON.
Home-page: https://github.com/SiDianaGit/csv_to_json_format
Author: Simone A Diana
Author-email: si_ap@hotmail.com
Classifier: Programming Language :: Python :: 3
Classifier: License :: OSI Approved :: MIT License
Classifier: Operating System :: OS Independent
Requires-Python: >=3.6
Requires-Dist: pandas
Dynamic: author
Dynamic: author-email
Dynamic: classifier
Dynamic: description
Dynamic: description-content-type
Dynamic: home-page
Dynamic: requires-dist
Dynamic: requires-python
Dynamic: summary
